inverter/.editorconfig
inverter/.flake8
inverter/.gitignore
inverter/__init__.py
inverter/__main__.py
inverter/api.py
inverter/connection.py
inverter/constants.py
inverter/daily_reset.py
inverter/data_types.py
inverter/definitions.py
inverter/exceptions.py
inverter/publish_loop.py
inverter/user_settings.py
inverter/validators.py
inverter/.github/workflows/tests.yml
inverter/cli/__init__.py
inverter/cli/cli_app.py
inverter/cli/dev.py
inverter/definitions/deye_2mppt.yaml
inverter/definitions/deye_2mppt_validations.yaml
inverter/definitions/deye_4mppt.yaml
inverter/definitions/deye_4mppt_validations.yaml
inverter/definitions/deye_sg04lp3.yaml
inverter/definitions/deye_sg04lp3_validations.yaml
inverter/tests/__init__.py
inverter/tests/fixtures.py
inverter/tests/test_api.py
inverter/tests/test_cli.py
inverter/tests/test_connection.py
inverter/tests/test_daily_reset.py
inverter/tests/test_definitions.py
inverter/tests/test_doctests.py
inverter/tests/test_project_setup.py
inverter/tests/test_readme.py
inverter/tests/test_user_settings.py
inverter/tests/test_validators.py
inverter/utilities/__init__.py
inverter/utilities/cli.py
inverter/utilities/modbus_converter.py
inverter_connect-0.13.0.dist-info/METADATA
inverter_connect-0.13.0.dist-info/WHEEL
inverter_connect-0.13.0.dist-info/entry_points.txt
inverter_connect-0.13.0.dist-info/top_level.txt
inverter_connect-0.13.0.dist-info/RECORD
