Metadata-Version: 2.1
Name: inverter-connect
Version: 0.13.0
Summary: Get information from Deye Microinverter
Author-email: Jens Diemer <inverter-connect@jensdiemer.de>
License: GPL-3.0-or-later
Project-URL: Documentation, https://github.com/jedie/inverter-connect
Project-URL: Source, https://github.com/jedie/inverter-connect
Requires-Python: <4,>=3.9
Requires-Dist: ha-services
Requires-Dist: backoff
Requires-Dist: paho-mqtt
Requires-Dist: msgspec
Requires-Dist: pyyaml
Requires-Dist: cli-base-utilities
Requires-Dist: click
Requires-Dist: rich-click
Requires-Dist: rich
Provides-Extra: dev
Requires-Dist: freezegun ; extra == 'dev'
Requires-Dist: manageprojects ; extra == 'dev'
Requires-Dist: bx-py-utils ; extra == 'dev'
Requires-Dist: pip-tools ; extra == 'dev'
Requires-Dist: tox ; extra == 'dev'
Requires-Dist: coverage ; extra == 'dev'
Requires-Dist: autopep8 ; extra == 'dev'
Requires-Dist: pyupgrade ; extra == 'dev'
Requires-Dist: flake8 ; extra == 'dev'
Requires-Dist: pyflakes ; extra == 'dev'
Requires-Dist: codespell ; extra == 'dev'
Requires-Dist: EditorConfig ; extra == 'dev'
Requires-Dist: safety ; extra == 'dev'
Requires-Dist: mypy ; extra == 'dev'
Requires-Dist: twine ; extra == 'dev'
Requires-Dist: darker[color,flynt,isort] ; extra == 'dev'
Requires-Dist: tomli ; extra == 'dev'
